toaster/__init__.py
toaster/helper.py
pytoaster-0.0.7.dist-info/LICENSE
pytoaster-0.0.7.dist-info/METADATA
pytoaster-0.0.7.dist-info/WHEEL
pytoaster-0.0.7.dist-info/top_level.txt
pytoaster-0.0.7.dist-info/RECORD
