Metadata-Version: 2.1
Name: pytoaster
Version: 0.0.7
Summary: Sends a telegram message to you when your code finish running
Home-page: https://github.com/zhunhung/toaster/
Author: Zhun Hung
Author-email: yongzhunhung@gmail.com
License: UNKNOWN
Platform: UNKNOWN
Classifier: Programming Language :: Python :: 3
Classifier: License :: OSI Approved :: MIT License
Classifier: Operating System :: OS Independent
Requires-Python: >=3.6
